maybetype/__init__.py
maybetype/const.py
py_maybetype-0.6.0.dist-info/METADATA
py_maybetype-0.6.0.dist-info/WHEEL
py_maybetype-0.6.0.dist-info/licenses/LICENSE
py_maybetype-0.6.0.dist-info/RECORD
