Metadata-Version: 2.4
Name: py-maybetype
Version: 0.6.0
Summary: A basic implementation of a maybe/option type in Python, largely inspired by Rust's Option.
Project-URL: Homepage, https://github.com/svioletg/py-maybetype
Project-URL: Repository, https://github.com/svioletg/py-maybetype
Project-URL: Documentation, https://py-maybetype.readthedocs.io/en/latest/
Project-URL: Changelog, https://github.com/svioletg/py-maybetype/blob/main/CHANGELOG.md
Project-URL: Issues, https://github.com/svioletg/py-maybetype/issues
Author: Seth 'Violet' Gibbs
License-Expression: MIT
License-File: LICENSE
Classifier: Development Status :: 4 - Beta
Classifier: Intended Audience :: Developers
Classifier: License :: OSI Approved :: MIT License
Classifier: Programming Language :: Python :: 3
Classifier: Programming Language :: Python :: 3.12
Classifier: Programming Language :: Python :: 3.13
Requires-Python: >=3.12
Provides-Extra: dev
Requires-Dist: pytest>=9.0.2; extra == 'dev'
Requires-Dist: ruff>=0.14.8; extra == 'dev'
Provides-Extra: docs
Requires-Dist: furo>=2025.12.19; extra == 'docs'
Requires-Dist: myst-parser>=4.0.1; extra == 'docs'
Requires-Dist: sphinx-autobuild>=2025.8.25; extra == 'docs'
Requires-Dist: sphinx<9.0,>=6.0; extra == 'docs'
